odoo/addons/bookstore_mgmt_google_books_api/README.rst
odoo/addons/bookstore_mgmt_google_books_api/__init__.py
odoo/addons/bookstore_mgmt_google_books_api/__manifest__.py
odoo/addons/bookstore_mgmt_google_books_api/i18n/bookstore_mgmt_google_books_api.pot
odoo/addons/bookstore_mgmt_google_books_api/i18n/ca.po
odoo/addons/bookstore_mgmt_google_books_api/i18n/es.po
odoo/addons/bookstore_mgmt_google_books_api/i18n/it.po
odoo/addons/bookstore_mgmt_google_books_api/models/__init__.py
odoo/addons/bookstore_mgmt_google_books_api/models/google_books_mixin.py
odoo/addons/bookstore_mgmt_google_books_api/models/product_product.py
odoo/addons/bookstore_mgmt_google_books_api/models/product_template.py
odoo/addons/bookstore_mgmt_google_books_api/readme/CONTRIBUTORS.md
odoo/addons/bookstore_mgmt_google_books_api/readme/DESCRIPTION.md
odoo/addons/bookstore_mgmt_google_books_api/readme/USAGE.md
odoo/addons/bookstore_mgmt_google_books_api/static/description/icon.png
odoo/addons/bookstore_mgmt_google_books_api/static/description/index.html
odoo/addons/bookstore_mgmt_google_books_api/tests/__init__.py
odoo/addons/bookstore_mgmt_google_books_api/tests/test_google_books_api.py
odoo/addons/bookstore_mgmt_google_books_api/views/product.xml
odoo_addon_bookstore_mgmt_google_books_api-17.0.1.2.0.2.dist-info/METADATA
odoo_addon_bookstore_mgmt_google_books_api-17.0.1.2.0.2.dist-info/WHEEL
odoo_addon_bookstore_mgmt_google_books_api-17.0.1.2.0.2.dist-info/top_level.txt
odoo_addon_bookstore_mgmt_google_books_api-17.0.1.2.0.2.dist-info/RECORD
