Metadata-Version: 2.1
Name: odoo-addon-bookstore_mgmt_google_books_api
Version: 17.0.1.2.0.2
Requires-Python: >=3.10
Requires-Dist: Unidecode
Requires-Dist: google-books-api-wrapper
Requires-Dist: odoo-addon-bookstore_mgmt>=17.0dev,<17.1dev
Requires-Dist: odoo-addon-web_notify>=17.0dev,<17.1dev
Requires-Dist: odoo>=17.0a,<17.1dev
Summary: Bookstore integration with Google Books API
Home-page: https://github.com/OCA/vertical-edition
License: AGPL-3
Author: APSL-Nagarro, Odoo Community Association (OCA)
Author-email: support@odoo-community.org
Classifier: Programming Language :: Python
Classifier: Framework :: Odoo
Classifier: Framework :: Odoo :: 17.0
Classifier: License :: OSI Approved :: GNU Affero General Public License v3
